powerline_xonsh/__init__.py
powerline_xonsh/segments.py
xontrib/powerline_binding.xsh
xontrib_powerline_binding-0.3.1.data/data/LICENSE.txt
xontrib_powerline_binding-0.3.1.dist-info/LICENSE.txt
xontrib_powerline_binding-0.3.1.dist-info/METADATA
xontrib_powerline_binding-0.3.1.dist-info/WHEEL
xontrib_powerline_binding-0.3.1.dist-info/top_level.txt
xontrib_powerline_binding-0.3.1.dist-info/RECORD
