Metadata-Version: 2.1
Name: xontrib-powerline-binding
Version: 0.3.1
Summary: Powerline binding for xonsh
Home-page: https://github.com/dyuri/xontrib-powerline-binding
Author: Gyuri Horák
Author-email: dyuri@horak.hu
License: MIT
Platform: any
Classifier: Environment :: Console
Classifier: Intended Audience :: End Users/Desktop
Classifier: Operating System :: OS Independent
Classifier: Programming Language :: Python :: 3
Classifier: Topic :: Desktop Environment
Classifier: Topic :: System :: Shells
Classifier: Topic :: System :: System Shells
Requires-Dist: powerline-status
